README.rst
setup.py
snipeitpyapi/Accessories.py
snipeitpyapi/Assets.py
snipeitpyapi/AssetsMaintenances.py
snipeitpyapi/Categories.py
snipeitpyapi/Company.py
snipeitpyapi/Components.py
snipeitpyapi/Consumables.py
snipeitpyapi/DataUtil.py
snipeitpyapi/Fieldsets.py
snipeitpyapi/Licenses.py
snipeitpyapi/Locations.py
snipeitpyapi/Maintenances.py
snipeitpyapi/Manufacturers.py
snipeitpyapi/Models.py
snipeitpyapi/StatusLabels.py
snipeitpyapi/Users.py
snipeitpyapi/__init__.py
snipeitpyapi.egg-info/PKG-INFO
snipeitpyapi.egg-info/SOURCES.txt
snipeitpyapi.egg-info/dependency_links.txt
snipeitpyapi.egg-info/not-zip-safe
snipeitpyapi.egg-info/requires.txt
snipeitpyapi.egg-info/top_level.txt