Metadata-Version: 2.1
Name: snipeitpyapi
Version: 1.6
Summary: Python library to access the SnipeIT API
Home-page: https://github.com/caiodelgadonew/SnipeIT-PythonAPI
Author: Jared Bloomer (Cox Automotive Inc.)
Author-email: jared.bloomer@coxautoinc.com
License: MIT
Platform: UNKNOWN
